causallib/__init__.py
causallib/analysis/__init__.py
causallib/contrib/__init__.py
causallib/contrib/faissknn.py
causallib/contrib/requirements.txt
causallib/contrib/adversarial_balancing/__init__.py
causallib/contrib/adversarial_balancing/adversarial_balancing.py
causallib/contrib/adversarial_balancing/classifier_selection.py
causallib/contrib/bicause_tree/__init__.py
causallib/contrib/bicause_tree/bicause_tree.py
causallib/contrib/bicause_tree/overlap_utils.py
causallib/contrib/hemm/__init__.py
causallib/contrib/hemm/gen_synthetic_data.py
causallib/contrib/hemm/hemm.py
causallib/contrib/hemm/hemm_api.py
causallib/contrib/hemm/hemm_metrics.py
causallib/contrib/hemm/hemm_outcome_models.py
causallib/contrib/hemm/hemm_utilities.py
causallib/contrib/hemm/load_ihdp_data.py
causallib/contrib/shared_sparsity_selection/__init__.py
causallib/contrib/shared_sparsity_selection/shared_sparsity_selection.py
causallib/contrib/sklearn_scorer_wrapper/__init__.py
causallib/contrib/sklearn_scorer_wrapper/sklearn_scorer_wrapper.py
causallib/contrib/tests/__init__.py
causallib/contrib/tests/test_adversarial_balancing.py
causallib/contrib/tests/test_bicause_tree.py
causallib/contrib/tests/test_hemm.py
causallib/contrib/tests/test_shared_sparsity_selection.py
causallib/contrib/tests/test_sklearn_scorer_wrapper.py
causallib/datasets/__init__.py
causallib/datasets/data_loader.py
causallib/datasets/data/acic_challenge_2016/x.csv
causallib/datasets/data/acic_challenge_2016/zymu_1.csv
causallib/datasets/data/acic_challenge_2016/zymu_10.csv
causallib/datasets/data/acic_challenge_2016/zymu_2.csv
causallib/datasets/data/acic_challenge_2016/zymu_3.csv
causallib/datasets/data/acic_challenge_2016/zymu_4.csv
causallib/datasets/data/acic_challenge_2016/zymu_5.csv
causallib/datasets/data/acic_challenge_2016/zymu_6.csv
causallib/datasets/data/acic_challenge_2016/zymu_7.csv
causallib/datasets/data/acic_challenge_2016/zymu_8.csv
causallib/datasets/data/acic_challenge_2016/zymu_9.csv
causallib-0.10.0.dist-info/licenses/LICENSE
causallib-0.10.0.dist-info/METADATA
causallib-0.10.0.dist-info/WHEEL
causallib-0.10.0.dist-info/top_level.txt
causallib-0.10.0.dist-info/RECORD
