Metadata-Version: 2.4
Name: causallib
Version: 0.10.0
Summary: A Python package for flexible and modular causal inference modeling
Home-page: https://github.com/BiomedSciAI/causallib
Author: Causal Machine Learning for Healthcare and Life Sciences, IBM Research Israel
License: Apache License 2.0
Project-URL: Documentation, https://causallib.readthedocs.io/en/latest/
Project-URL: Source Code, https://github.com/BiomedSciAI/causallib
Project-URL: Bug Tracker, https://github.com/BiomedSciAI/causallib/issues
Keywords: causal inference effect estimation causality
Classifier: Programming Language :: Python :: 3.6
Classifier: Programming Language :: Python :: 3.7
Classifier: Programming Language :: Python :: 3.8
Classifier: Programming Language :: Python :: 3.9
Classifier: License :: OSI Approved :: Apache Software License
Classifier: Development Status :: 4 - Beta
Classifier: Topic :: Scientific/Engineering
Classifier: Intended Audience :: Science/Research
License-File: LICENSE
Requires-Dist: pandas<3,>=0.25.2
Requires-Dist: scipy<2,>=0.19
Requires-Dist: statsmodels<1,>=0.9
Requires-Dist: networkx<4,>=1.1
Requires-Dist: numpy<3,>=1.13
Requires-Dist: scikit-learn<2,>=0.20
Requires-Dist: matplotlib<4,>=2.2
Requires-Dist: dataclasses>=0.8; python_version < "3.7"
Provides-Extra: contrib
Requires-Dist: torch>=1.2.0; extra == "contrib"
Requires-Dist: faiss-cpu~=1.7.0; python_version < "3.12" and extra == "contrib"
Requires-Dist: faiss-cpu~=1.8.0; python_version >= "3.12" and extra == "contrib"
Provides-Extra: docs
Requires-Dist: sphinx==4.4.0; extra == "docs"
Requires-Dist: m2r2; extra == "docs"
Requires-Dist: sphinx-rtd-theme; extra == "docs"
Dynamic: author
Dynamic: classifier
Dynamic: description
Dynamic: description-content-type
Dynamic: home-page
Dynamic: keywords
Dynamic: license
Dynamic: license-file
Dynamic: project-url
Dynamic: provides-extra
Dynamic: requires-dist
Dynamic: summary
